shiva_ai/__init__.py
shiva_ai/main.py
shiva_ai-0.0.1.dist-info/METADATA
shiva_ai-0.0.1.dist-info/WHEEL
shiva_ai-0.0.1.dist-info/top_level.txt
shiva_ai-0.0.1.dist-info/RECORD
